{
"skeleton": { "hash": "Ccm+uBiktcw", "spine": "4.1.24", "images": "./Images/", "audio": "/Users/phucpham/Documents/phucpham/After Effects/Freelancer/Atuan/z_GameKid/1_Start_10:2023/4_Shape/3_boat/grap" },
"bones": [
	{ "name": "root", "x": -1054.7, "y": 742.41 },
	{
		"name": "bone11",
		"parent": "root",
		"length": 92.32,
		"rotation": 2.73,
		"x": 240.48,
		"y": -236.66,
		"scaleX": 0.8,
		"scaleY": 0.8
	},
	{ "name": "body chim 3", "parent": "bone11", "length": 61.77, "rotation": 161.85, "x": 380.2, "y": -127.8 },
	{ "name": "chim 3 canh 2", "parent": "body chim 3", "length": 86.19, "rotation": -141.68, "x": 22.68, "y": -17.88 },
	{ "name": "chim 3 canh 1", "parent": "body chim 3", "length": 68.72, "rotation": -17.79, "x": 43.36, "y": -7.92 },
	{ "name": "body chim 4", "parent": "bone11", "length": 77.7, "rotation": 24.49, "x": 261.85, "y": 18.01 },
	{ "name": "chim 2 canh 2", "parent": "body chim 4", "length": 54.14, "rotation": 102.39, "x": 26.9, "y": 10.24 },
	{ "name": "chim 2 canh 1", "parent": "body chim 4", "length": 33.56, "rotation": 17.78, "x": 51.05, "y": 13.19 },
	{ "name": "chim 1", "parent": "bone11", "length": 71.09, "rotation": 4.71, "x": 3.81, "y": 135.85 },
	{ "name": "wing_1", "parent": "chim 1", "length": 26.5, "rotation": 106.55, "x": 27.11, "y": 21.56 },
	{ "name": "wing_1_2", "parent": "wing_1", "length": 63.1, "rotation": 7.17, "x": 26.5 },
	{ "name": "wing_2", "parent": "chim 1", "length": 29.32, "rotation": -68.52, "x": 47.92, "y": -16.49 },
	{ "name": "wing_2_2", "parent": "wing_2", "length": 60.71, "rotation": 1.99, "x": 29.32 }
],
"slots": [
	{ "name": "chim 1", "bone": "chim 1" },
	{ "name": "chim 2 canh 1", "bone": "chim 2 canh 1" },
	{ "name": "body chim 2", "bone": "body chim 4" },
	{ "name": "chim 2 canh 2", "bone": "chim 2 canh 2" },
	{ "name": "chim 3 canh 1", "bone": "chim 3 canh 1" },
	{ "name": "body chim 3", "bone": "body chim 3" },
	{ "name": "chim 3 canh 2", "bone": "chim 3 canh 2" },
	{ "name": "fly_path_chim_1", "bone": "root", "attachment": "fly_path_chim_1" },
	{ "name": "Fly_path_chim_3", "bone": "root", "attachment": "Fly_path_chim_3" },
	{ "name": "fly_path_chim_4", "bone": "root", "attachment": "fly_path_chim_4" }
],
"path": [
	{
		"name": "fly_path_chim_1",
		"bones": [ "chim 1" ],
		"target": "fly_path_chim_1"
	},
	{
		"name": "Fly_path_chim_3",
		"order": 1,
		"bones": [ "body chim 3" ],
		"target": "Fly_path_chim_3"
	},
	{
		"name": "fly_path_chim_4",
		"order": 2,
		"bones": [ "body chim 4" ],
		"target": "fly_path_chim_4"
	}
],
"skins": [
	{
		"name": "default",
		"attachments": {
			"body chim 2": {
				"body chim 2": { "x": 18.31, "y": 4.2, "rotation": -27.22, "width": 185, "height": 79 }
			},
			"body chim 3": {
				"body chim 3": { "x": 10.06, "y": -7.2, "rotation": -164.58, "width": 183, "height": 68 }
			},
			"chim 1": {
				"chim 1": {
					"type": "mesh",
					"uvs": [ 0.00327, 0, 0.01221, 0, 0.28197, 0.07309, 0.33399, 0.10905, 0.41124, 0.23529, 0.49586, 0.35594, 0.54822, 0.41214, 0.63304, 0.41279, 0.79115, 0.40215, 0.92447, 0.44893, 0.69772, 0.52741, 0.70015, 0.54576, 0.78677, 0.622, 0.97417, 0.77004, 0.99531, 0.82089, 0.99404, 0.92219, 0.97063, 0.99282, 0.96437, 1, 0.94295, 0.99336, 0.84433, 0.92706, 0.81751, 0.89852, 0.77512, 0.87297, 0.68463, 0.79175, 0.49128, 0.54902, 0.05963, 0.59595, 0.0295, 0.45523, 0.35086, 0.42343, 0.20776, 0.30117, 0.15209, 0.24326, 0.0778, 0.1502, 0.07184, 0.13007, 0.05362, 0.11162, 0.00626, 0.01841 ],
					"triangles": [ 32, 0, 1, 32, 1, 2, 31, 32, 2, 30, 31, 2, 29, 30, 2, 3, 28, 29, 3, 29, 2, 28, 3, 4, 27, 28, 4, 27, 4, 5, 26, 27, 5, 26, 5, 6, 10, 7, 8, 10, 8, 9, 23, 26, 6, 10, 23, 6, 10, 6, 7, 24, 25, 26, 24, 26, 23, 23, 12, 22, 11, 23, 10, 12, 23, 11, 22, 12, 13, 21, 22, 13, 21, 13, 14, 20, 21, 14, 15, 20, 14, 19, 20, 15, 15, 18, 19, 16, 18, 15, 17, 18, 16 ],
					"vertices": [ 1, 10, 106.58, 8.28, 1, 1, 10, 105.79, 6.98, 1, 1, 10, 64.85, -21.9, 1, 1, 10, 51.79, -24.36, 1, 2, 9, 43.75, -15.6, 0.01086, 10, 15.17, -17.63, 0.98914, 2, 8, 39.62, 33.08, 0.03241, 9, 7.48, -15.28, 0.96759, 2, 8, 46.47, 16.56, 0.65823, 9, -10.31, -17.14, 0.34177, 2, 8, 60.75, 14.55, 0.97265, 9, -16.31, -30.25, 0.02735, 1, 8, 87.78, 14.03, 1, 1, 8, 108.62, -1.67, 1, 2, 8, 67.62, -18.23, 0.4484, 11, 8.83, 17.7, 0.5516, 3, 8, 67.38, -23.31, 0.1782, 11, 13.47, 15.62, 0.80272, 12, -15.3, 16.16, 0.01907, 2, 11, 39, 18.38, 0.09495, 12, 10.32, 18.04, 0.90505, 1, 12, 61.73, 24.48, 1, 1, 12, 75.62, 20.38, 1, 1, 12, 99.53, 5.88, 1, 1, 12, 114.23, -7.52, 1, 1, 12, 115.39, -9.45, 1, 1, 12, 111.95, -11.64, 1, 1, 12, 87.65, -16.67, 1, 1, 12, 78.55, -16.55, 1, 1, 12, 68.8, -19.13, 1, 1, 12, 41.67, -20.87, 1, 2, 8, 32.05, -19.67, 0.43277, 11, -2.85, -15.93, 0.56723, 1, 8, -42.38, -23.15, 1, 1, 8, -42.51, 16.02, 1, 2, 8, 12.8, 17.75, 0.43261, 9, 0.43, 14.8, 0.56739, 2, 9, 41.13, 23.39, 0.05003, 10, 17.43, 21.38, 0.94997, 1, 10, 36.01, 21.24, 1, 1, 10, 64.53, 18.81, 1, 1, 10, 69.81, 16.81, 1, 1, 10, 75.77, 16.84, 1, 1, 10, 101.96, 10.47, 1 ],
					"hull": 33,
					"edges": [ 0, 64, 0, 2, 2, 4, 4, 6, 6, 8, 8, 10, 10, 12, 12, 14, 20, 22, 22, 24, 24, 26, 26, 28, 28, 30, 30, 32, 32, 34, 34, 36, 36, 38, 38, 40, 40, 42, 42, 44, 44, 46, 52, 54, 54, 56, 56, 58, 58, 60, 60, 62, 62, 64, 50, 52, 48, 50, 14, 16, 16, 18, 18, 20, 46, 48 ],
					"width": 170,
					"height": 276
				}
			},
			"chim 2 canh 1": {
				"chim 2 canh 1": { "x": 8.15, "y": -27.9, "rotation": -45, "width": 84, "height": 95 }
			},
			"chim 2 canh 2": {
				"chim 2 canh 2": { "x": 50.41, "y": 30.8, "rotation": -129.61, "width": 173, "height": 88 }
			},
			"chim 3 canh 1": {
				"chim 3 canh 1": { "x": 49.04, "y": 4.67, "rotation": -146.78, "width": 118, "height": 61 }
			},
			"chim 3 canh 2": {
				"chim 3 canh 2": { "x": 61.41, "y": 3.21, "rotation": -22.9, "width": 161, "height": 63 }
			},
			"fly_path_chim_1": {
				"fly_path_chim_1": {
					"type": "path",
					"lengths": [ 1621.85, 3401.65, 6792.69 ],
					"vertexCount": 9,
					"vertices": [ -1068.93, -412.87, -586.57, -461.4, -102.27, -510.12, 704.62, -555.87, 1032.35, -550.01, 1352.91, -544.28, 2371.87, -377.62, 2801.84, -361.54, 3103.58, -350.26 ]
				}
			},
			"Fly_path_chim_3": {
				"Fly_path_chim_3": {
					"type": "path",
					"lengths": [ 1310.46, 2349.75, 3714.17, 7424.95 ],
					"vertexCount": 12,
					"vertices": [ -1123.67, -500.09, -632, -472.78, -140.33, -445.46, 322.05, -385.66, 673.63, -361.22, 1025.21, -336.77, 1419.29, -303.2, 1711.33, -309.85, 2018.98, -316.84, 2641.17, -349.27, 3071.93, -255.87, 3371.22, -190.98 ]
				}
			},
			"fly_path_chim_4": {
				"fly_path_chim_4": {
					"type": "path",
					"lengths": [ 1489.55, 3468.81, 6926.75 ],
					"vertexCount": 9,
					"vertices": [ -1103.66, -452.38, -603.67, -480.76, -103.69, -509.15, 632.19, -487.37, 885.28, -470.9, 1241.08, -447.75, 1924.4, -392.24, 2827.11, -111.91, 3354.71, 51.93 ]
				}
			}
		}
	}
],
"animations": {
	"bird_1_idle": {
		"slots": {
			"body chim 3": {
				"attachment": [
					{ "name": "body chim 3" }
				]
			},
			"chim 3 canh 1": {
				"attachment": [
					{ "name": "chim 3 canh 1" }
				]
			},
			"chim 3 canh 2": {
				"attachment": [
					{ "name": "chim 3 canh 2" }
				]
			}
		},
		"bones": {
			"body chim 3": {
				"rotate": [
					{ "value": -150.82 }
				],
				"translate": [
					{ "x": 631.83, "y": -544.01 },
					{ "time": 0.4667, "x": 631.83, "y": -531.36 },
					{ "time": 0.8333, "x": 631.83, "y": -547 },
					{ "time": 1.2, "x": 631.83, "y": -535.01 },
					{ "time": 1.6667, "x": 631.83, "y": -549.09 },
					{ "time": 2.1333, "x": 631.83, "y": -528.2 },
					{ "time": 2.5, "x": 631.83, "y": -554.55 },
					{ "time": 2.9, "x": 631.83, "y": -528.76 },
					{ "time": 3.3333, "x": 631.83, "y": -544.01 }
				],
				"scale": [
					{ "y": -1 }
				]
			},
			"chim 3 canh 1": {
				"rotate": [
					{
						"curve": [ 0.156, 0, 0.311, 21.08 ]
					},
					{
						"time": 0.4667,
						"value": 21.08,
						"curve": [ 0.589, 21.08, 0.711, 0 ]
					},
					{
						"time": 0.8333,
						"curve": [ 0.956, 0, 1.078, 21.08 ]
					},
					{
						"time": 1.2,
						"value": 21.08,
						"curve": [ 1.356, 21.08, 1.511, 0 ]
					},
					{
						"time": 1.6667,
						"curve": [ 1.822, 0, 1.978, 21.08 ]
					},
					{
						"time": 2.1333,
						"value": 21.08,
						"curve": [ 2.256, 21.08, 2.378, 0 ]
					},
					{
						"time": 2.5,
						"curve": [ 2.622, 0, 2.744, 21.08 ]
					},
					{
						"time": 2.8667,
						"value": 21.08,
						"curve": [ 3.022, 21.08, 3.178, 7.03 ]
					},
					{ "time": 3.3333 }
				]
			},
			"chim 3 canh 2": {
				"rotate": [
					{
						"curve": [ 0.156, 0, 0.311, -11.48 ]
					},
					{
						"time": 0.4667,
						"value": -11.48,
						"curve": [ 0.589, -11.48, 0.711, 0 ]
					},
					{
						"time": 0.8333,
						"curve": [ 0.956, 0, 1.078, -11.48 ]
					},
					{
						"time": 1.2,
						"value": -11.48,
						"curve": [ 1.356, -11.48, 1.511, 0 ]
					},
					{
						"time": 1.6667,
						"curve": [ 1.822, 0, 1.978, -11.48 ]
					},
					{
						"time": 2.1333,
						"value": -11.48,
						"curve": [ 2.256, -11.48, 2.378, 0 ]
					},
					{
						"time": 2.5,
						"curve": [ 2.622, 0, 2.744, -11.48 ]
					},
					{
						"time": 2.8667,
						"value": -11.48,
						"curve": [ 3.022, -11.48, 3.178, -3.83 ]
					},
					{ "time": 3.3333 }
				]
			}
		}
	},
	"bird_2_idle": {
		"slots": {
			"body chim 2": {
				"attachment": [
					{ "name": "body chim 2" }
				]
			},
			"chim 2 canh 1": {
				"attachment": [
					{ "name": "chim 2 canh 1" }
				]
			},
			"chim 2 canh 2": {
				"attachment": [
					{ "name": "chim 2 canh 2" }
				]
			}
		},
		"bones": {
			"body chim 4": {
				"translate": [
					{ "x": 720.31, "y": -706.5 },
					{ "time": 0.6667, "x": 712.69, "y": -686.31 },
					{ "time": 1.3333, "x": 720.31, "y": -706.5 }
				]
			},
			"chim 2 canh 1": {
				"rotate": [
					{ "value": 19.76 },
					{ "time": 0.6667, "value": 5.08 },
					{ "time": 1.3333, "value": 19.76 }
				]
			},
			"chim 2 canh 2": {
				"rotate": [
					{},
					{ "time": 0.6667, "value": 19.49 },
					{ "time": 1.3333 }
				]
			}
		}
	},
	"bird_3_idle": {
		"slots": {
			"chim 1": {
				"attachment": [
					{ "name": "chim 1" }
				]
			}
		},
		"bones": {
			"chim 1": {
				"rotate": [
					{ "value": -5.41 },
					{ "time": 1.6667, "value": -1.52 },
					{ "time": 3.6667, "value": -5.41 }
				],
				"translate": [
					{
						"x": 929.51,
						"y": -802.67,
						"curve": [ 0.347, 929.51, 1.319, 972.86, 0.347, -802.67, 1.319, -797.94 ]
					},
					{
						"time": 1.6667,
						"x": 986.63,
						"y": -794.98,
						"curve": [ 2.333, 1013.07, 3, 929.51, 2.333, -789.3, 3, -802.67 ]
					},
					{ "time": 3.6667, "x": 929.51, "y": -802.67 }
				],
				"scale": [
					{
						"x": 0.95,
						"curve": [ 0.347, 0.95, 1.319, 1, 0.347, 1, 1.319, 1 ]
					},
					{
						"time": 1.6667,
						"curve": [ 2.333, 1, 3, 0.95, 2.333, 1, 3, 1 ]
					},
					{ "time": 3.6667, "x": 0.95 }
				]
			}
		}
	},
	"fly_1": {
		"slots": {
			"chim 1": {
				"attachment": [
					{ "time": 1.6667, "name": "chim 1" }
				]
			}
		},
		"bones": {
			"wing_1": {
				"rotate": [
					{ "time": 1.6667 },
					{ "time": 2.3333, "value": -4.59 },
					{ "time": 3 },
					{ "time": 3.6667, "value": -4.59 },
					{ "time": 4.3333 },
					{ "time": 5, "value": -4.59 },
					{ "time": 5.6667 },
					{ "time": 6.3333, "value": -4.59 },
					{ "time": 7 },
					{ "time": 7.6667, "value": -4.59 },
					{ "time": 8.3333 },
					{ "time": 9, "value": -4.59 },
					{ "time": 9.6667 },
					{ "time": 10.3333, "value": -4.59 },
					{ "time": 11 },
					{ "time": 11.6667, "value": -4.59 },
					{ "time": 16.6667 },
					{ "time": 17.3333, "value": -4.59 },
					{ "time": 18 },
					{ "time": 18.6667, "value": -4.59 },
					{ "time": 19.3333 },
					{ "time": 20, "value": -4.59 },
					{ "time": 20.6667 },
					{ "time": 21.3333, "value": -4.59 },
					{ "time": 22 },
					{ "time": 22.6667, "value": -4.59 },
					{ "time": 23.3333 },
					{ "time": 24, "value": -4.59 },
					{ "time": 24.6667 },
					{ "time": 25.3333, "value": -4.59 },
					{ "time": 26 },
					{ "time": 26.6667, "value": -4.59 }
				]
			},
			"wing_1_2": {
				"rotate": [
					{ "time": 1.6667 },
					{ "time": 2.3333, "value": -17.36 },
					{ "time": 3 },
					{ "time": 3.6667, "value": -17.36 },
					{ "time": 4.3333 },
					{ "time": 5, "value": -17.36 },
					{ "time": 5.6667 },
					{ "time": 6.3333, "value": -17.36 },
					{ "time": 7 },
					{ "time": 7.6667, "value": -17.36 },
					{ "time": 8.3333 },
					{ "time": 9, "value": -17.36 },
					{ "time": 9.6667 },
					{ "time": 10.3333, "value": -17.36 },
					{ "time": 11 },
					{ "time": 11.6667, "value": -17.36 },
					{ "time": 16.6667 },
					{ "time": 17.3333, "value": -17.36 },
					{ "time": 18 },
					{ "time": 18.6667, "value": -17.36 },
					{ "time": 19.3333 },
					{ "time": 20, "value": -17.36 },
					{ "time": 20.6667 },
					{ "time": 21.3333, "value": -17.36 },
					{ "time": 22 },
					{ "time": 22.6667, "value": -17.36 },
					{ "time": 23.3333 },
					{ "time": 24, "value": -17.36 },
					{ "time": 24.6667 },
					{ "time": 25.3333, "value": -17.36 },
					{ "time": 26 },
					{ "time": 26.6667, "value": -17.36 }
				]
			},
			"wing_2": {
				"rotate": [
					{ "time": 1.6667 },
					{ "time": 2.3333, "value": 4.76 },
					{ "time": 3 },
					{ "time": 3.6667, "value": 4.76 },
					{ "time": 4.3333 },
					{ "time": 5, "value": 4.76 },
					{ "time": 5.6667 },
					{ "time": 6.3333, "value": 4.76 },
					{ "time": 7 },
					{ "time": 7.6667, "value": 4.76 },
					{ "time": 8.3333 },
					{ "time": 9, "value": 4.76 },
					{ "time": 9.6667 },
					{ "time": 10.3333, "value": 4.76 },
					{ "time": 11 },
					{ "time": 11.6667, "value": 4.76 },
					{ "time": 16.6667 },
					{ "time": 17.3333, "value": 4.76 },
					{ "time": 18 },
					{ "time": 18.6667, "value": 4.76 },
					{ "time": 19.3333 },
					{ "time": 20, "value": 4.76 },
					{ "time": 20.6667 },
					{ "time": 21.3333, "value": 4.76 },
					{ "time": 22 },
					{ "time": 22.6667, "value": 4.76 },
					{ "time": 23.3333 },
					{ "time": 24, "value": 4.76 },
					{ "time": 24.6667 },
					{ "time": 25.3333, "value": 4.76 },
					{ "time": 26 },
					{ "time": 26.6667, "value": 4.76 }
				]
			},
			"wing_2_2": {
				"rotate": [
					{ "time": 1.6667 },
					{ "time": 2.3333, "value": 17.19 },
					{ "time": 3 },
					{ "time": 3.6667, "value": 17.19 },
					{ "time": 4.3333 },
					{ "time": 5, "value": 17.19 },
					{ "time": 5.6667 },
					{ "time": 6.3333, "value": 17.19 },
					{ "time": 7 },
					{ "time": 7.6667, "value": 17.19 },
					{ "time": 8.3333 },
					{ "time": 9, "value": 17.19 },
					{ "time": 9.6667 },
					{ "time": 10.3333, "value": 17.19 },
					{ "time": 11 },
					{ "time": 11.6667, "value": 17.19 },
					{ "time": 16.6667 },
					{ "time": 17.3333, "value": 17.19 },
					{ "time": 18 },
					{ "time": 18.6667, "value": 17.19 },
					{ "time": 19.3333 },
					{ "time": 20, "value": 17.19 },
					{ "time": 20.6667 },
					{ "time": 21.3333, "value": 17.19 },
					{ "time": 22 },
					{ "time": 22.6667, "value": 17.19 },
					{ "time": 23.3333 },
					{ "time": 24, "value": 17.19 },
					{ "time": 24.6667 },
					{ "time": 25.3333, "value": 17.19 },
					{ "time": 26 },
					{ "time": 26.6667, "value": 17.19 }
				]
			}
		},
		"path": {
			"fly_path_chim_1": {
				"position": [
					{ "time": 1.6667 },
					{ "time": 11.6667, "value": 1.162, "curve": "stepped" },
					{ "time": 16.6667 },
					{ "time": 26.6667, "value": 1.162 }
				]
			}
		}
	},
	"fly_3": {
		"slots": {
			"body chim 3": {
				"attachment": [
					{ "time": 0.8333, "name": "body chim 3" }
				]
			},
			"chim 3 canh 1": {
				"attachment": [
					{ "time": 0.8333, "name": "chim 3 canh 1" }
				]
			},
			"chim 3 canh 2": {
				"attachment": [
					{ "time": 0.8333, "name": "chim 3 canh 2" }
				]
			}
		},
		"bones": {
			"body chim 3": {
				"scale": [
					{ "time": 0.8333, "y": -1 }
				]
			},
			"chim 3 canh 1": {
				"rotate": [
					{ "time": 0.8333, "value": -31.78 },
					{ "time": 1.5, "value": -8.91 },
					{ "time": 2.1667, "value": -31.78 },
					{ "time": 2.8333, "value": -8.91 },
					{ "time": 3.5, "value": -31.78 },
					{ "time": 4.1667, "value": -8.91 },
					{ "time": 4.8333, "value": -31.78 },
					{ "time": 5.5, "value": -8.91 },
					{ "time": 6.1667, "value": -31.78 },
					{ "time": 6.8333, "value": -8.91 },
					{ "time": 7.5, "value": -31.78 },
					{ "time": 8.1667, "value": -8.91 },
					{ "time": 8.8333, "value": -31.78 },
					{ "time": 9.5, "value": -8.91 },
					{ "time": 10.1667, "value": -31.78 },
					{ "time": 10.8333, "value": -8.91 },
					{ "time": 12.5, "value": -31.78 },
					{ "time": 13.1667, "value": -8.91 },
					{ "time": 13.8333, "value": -31.78 },
					{ "time": 14.5, "value": -8.91 },
					{ "time": 15.1667, "value": -31.78 },
					{ "time": 15.8333, "value": -8.91 },
					{ "time": 16.5, "value": -31.78 },
					{ "time": 17.1667, "value": -8.91 },
					{ "time": 17.8333, "value": -31.78 },
					{ "time": 18.5, "value": -8.91 },
					{ "time": 19.1667, "value": -31.78 },
					{ "time": 19.8333, "value": -8.91 },
					{ "time": 20.5, "value": -31.78 },
					{ "time": 21.1667, "value": -8.91 },
					{ "time": 21.8333, "value": -31.78 },
					{ "time": 22.5, "value": -8.91 },
					{ "time": 25.0333, "value": -31.78 },
					{ "time": 25.7, "value": -8.91 },
					{ "time": 26.3667, "value": -31.78 },
					{ "time": 27.0333, "value": -8.91 },
					{ "time": 27.7, "value": -31.78 },
					{ "time": 28.3667, "value": -8.91 },
					{ "time": 29.0333, "value": -31.78 },
					{ "time": 29.7, "value": -8.91 },
					{ "time": 30.3667, "value": -31.78 },
					{ "time": 31.0333, "value": -8.91 },
					{ "time": 31.7, "value": -31.78 },
					{ "time": 32.3667, "value": -8.91 },
					{ "time": 33.0333, "value": -31.78 },
					{ "time": 33.7, "value": -8.91 },
					{ "time": 34.3667, "value": -31.78 },
					{ "time": 35.0333, "value": -8.91 }
				]
			},
			"chim 3 canh 2": {
				"rotate": [
					{ "time": 0.8333 },
					{ "time": 1.5, "value": -20.08 },
					{ "time": 2.1667 },
					{ "time": 2.8333, "value": -20.08 },
					{ "time": 3.5 },
					{ "time": 4.1667, "value": -20.08 },
					{ "time": 4.8333 },
					{ "time": 5.5, "value": -20.08 },
					{ "time": 6.1667 },
					{ "time": 6.8333, "value": -20.08 },
					{ "time": 7.5 },
					{ "time": 8.1667, "value": -20.08 },
					{ "time": 8.8333 },
					{ "time": 9.5, "value": -20.08 },
					{ "time": 10.1667 },
					{ "time": 10.8333, "value": -20.08 },
					{ "time": 12.5 },
					{ "time": 13.1667, "value": -20.08 },
					{ "time": 13.8333 },
					{ "time": 14.5, "value": -20.08 },
					{ "time": 15.1667 },
					{ "time": 15.8333, "value": -20.08 },
					{ "time": 16.5 },
					{ "time": 17.1667, "value": -20.08 },
					{ "time": 17.8333 },
					{ "time": 18.5, "value": -20.08 },
					{ "time": 19.1667 },
					{ "time": 19.8333, "value": -20.08 },
					{ "time": 20.5 },
					{ "time": 21.1667, "value": -20.08 },
					{ "time": 21.8333 },
					{ "time": 22.5, "value": -20.08 },
					{ "time": 25.0333 },
					{ "time": 25.7, "value": -20.08 },
					{ "time": 26.3667 },
					{ "time": 27.0333, "value": -20.08 },
					{ "time": 27.7 },
					{ "time": 28.3667, "value": -20.08 },
					{ "time": 29.0333 },
					{ "time": 29.7, "value": -20.08 },
					{ "time": 30.3667 },
					{ "time": 31.0333, "value": -20.08 },
					{ "time": 31.7 },
					{ "time": 32.3667, "value": -20.08 },
					{ "time": 33.0333 },
					{ "time": 33.7, "value": -20.08 },
					{ "time": 34.3667 },
					{ "time": 35.0333, "value": -20.08 }
				],
				"translate": [
					{ "time": 0.8333, "x": 0.09, "y": 6.02 }
				]
			}
		},
		"path": {
			"Fly_path_chim_3": {
				"position": [
					{ "time": 0.8333 },
					{ "time": 10.8333, "value": 1, "curve": "stepped" },
					{ "time": 12.5 },
					{ "time": 22.5, "value": 1 },
					{ "time": 25.0333 },
					{ "time": 35.0333, "value": 1 }
				]
			}
		}
	},
	"fly_4": {
		"slots": {
			"body chim 2": {
				"attachment": [
					{ "name": "body chim 2" }
				]
			},
			"chim 2 canh 1": {
				"attachment": [
					{ "name": "chim 2 canh 1" }
				]
			},
			"chim 2 canh 2": {
				"attachment": [
					{ "name": "chim 2 canh 2" }
				]
			}
		},
		"bones": {
			"chim 2 canh 1": {
				"rotate": [
					{ "value": 57.31 },
					{ "time": 0.6667, "value": 9.25 },
					{ "time": 1.3333, "value": 57.31 },
					{ "time": 2, "value": 9.25 },
					{ "time": 2.6667, "value": 57.31 },
					{ "time": 3.3333, "value": 9.25 },
					{ "time": 4, "value": 57.31 },
					{ "time": 4.6667, "value": 9.25 },
					{ "time": 5.3333, "value": 57.31 },
					{ "time": 6, "value": 9.25 },
					{ "time": 6.6667, "value": 57.31 },
					{ "time": 7.3333, "value": 9.25 },
					{ "time": 8, "value": 57.31 },
					{ "time": 8.6667, "value": 9.25 },
					{ "time": 9.3333, "value": 57.31 },
					{ "time": 10, "value": 9.25 },
					{ "time": 13.3333, "value": 57.31 },
					{ "time": 14, "value": 9.25 },
					{ "time": 14.6667, "value": 57.31 },
					{ "time": 15.3333, "value": 9.25 },
					{ "time": 16, "value": 57.31 },
					{ "time": 16.6667, "value": 9.25 },
					{ "time": 17.3333, "value": 57.31 },
					{ "time": 18, "value": 9.25 },
					{ "time": 18.6667, "value": 57.31 },
					{ "time": 19.3333, "value": 9.25 },
					{ "time": 20, "value": 57.31 },
					{ "time": 20.6667, "value": 9.25 },
					{ "time": 21.3333, "value": 57.31 },
					{ "time": 22, "value": 9.25 },
					{ "time": 22.6667, "value": 57.31 },
					{ "time": 23.3333, "value": 9.25 },
					{ "time": 26.6667, "value": 57.31 },
					{ "time": 27.3333, "value": 9.25 },
					{ "time": 28, "value": 57.31 },
					{ "time": 28.6667, "value": 9.25 },
					{ "time": 29.3333, "value": 57.31 },
					{ "time": 30, "value": 9.25 },
					{ "time": 30.6667, "value": 57.31 },
					{ "time": 31.3333, "value": 9.25 },
					{ "time": 32, "value": 57.31 },
					{ "time": 32.6667, "value": 9.25 },
					{ "time": 33.3333, "value": 57.31 },
					{ "time": 34, "value": 9.25 },
					{ "time": 34.6667, "value": 57.31 },
					{ "time": 35.3333, "value": 9.25 },
					{ "time": 36, "value": 57.31 },
					{ "time": 36.6667, "value": 9.25 }
				]
			},
			"chim 2 canh 2": {
				"rotate": [
					{},
					{ "time": 0.6667, "value": 43.11 },
					{ "time": 1.3333 },
					{ "time": 2, "value": 43.11 },
					{ "time": 2.6667 },
					{ "time": 3.3333, "value": 43.11 },
					{ "time": 4 },
					{ "time": 4.6667, "value": 43.11 },
					{ "time": 5.3333 },
					{ "time": 6, "value": 43.11 },
					{ "time": 6.6667 },
					{ "time": 7.3333, "value": 43.11 },
					{ "time": 8 },
					{ "time": 8.6667, "value": 43.11 },
					{ "time": 9.3333 },
					{ "time": 10, "value": 43.11 },
					{ "time": 13.3333 },
					{ "time": 14, "value": 43.11 },
					{ "time": 14.6667 },
					{ "time": 15.3333, "value": 43.11 },
					{ "time": 16 },
					{ "time": 16.6667, "value": 43.11 },
					{ "time": 17.3333 },
					{ "time": 18, "value": 43.11 },
					{ "time": 18.6667 },
					{ "time": 19.3333, "value": 43.11 },
					{ "time": 20 },
					{ "time": 20.6667, "value": 43.11 },
					{ "time": 21.3333 },
					{ "time": 22, "value": 43.11 },
					{ "time": 22.6667 },
					{ "time": 23.3333, "value": 43.11 },
					{ "time": 26.6667 },
					{ "time": 27.3333, "value": 43.11 },
					{ "time": 28 },
					{ "time": 28.6667, "value": 43.11 },
					{ "time": 29.3333 },
					{ "time": 30, "value": 43.11 },
					{ "time": 30.6667 },
					{ "time": 31.3333, "value": 43.11 },
					{ "time": 32 },
					{ "time": 32.6667, "value": 43.11 },
					{ "time": 33.3333 },
					{ "time": 34, "value": 43.11 },
					{ "time": 34.6667 },
					{ "time": 35.3333, "value": 43.11 },
					{ "time": 36 },
					{ "time": 36.6667, "value": 43.11 }
				]
			}
		},
		"path": {
			"fly_path_chim_4": {
				"position": [
					{},
					{ "time": 10, "value": 1, "curve": "stepped" },
					{ "time": 13.3333 },
					{ "time": 23.3333, "value": 1, "curve": "stepped" },
					{ "time": 26.6667 },
					{ "time": 36.6667, "value": 1 }
				]
			}
		}
	},
	"fly_all": {
		"slots": {
			"body chim 2": {
				"attachment": [
					{ "time": 12.9667, "name": "body chim 2" }
				]
			},
			"body chim 3": {
				"attachment": [
					{ "time": 1.9667, "name": "body chim 3" }
				]
			},
			"chim 1": {
				"attachment": [
					{ "time": 0.2667, "name": "chim 1" }
				]
			},
			"chim 2 canh 1": {
				"attachment": [
					{ "time": 12.9667, "name": "chim 2 canh 1" }
				]
			},
			"chim 2 canh 2": {
				"attachment": [
					{ "time": 12.9667, "name": "chim 2 canh 2" }
				]
			},
			"chim 3 canh 1": {
				"attachment": [
					{ "time": 1.9667, "name": "chim 3 canh 1" }
				]
			},
			"chim 3 canh 2": {
				"attachment": [
					{ "time": 1.9667, "name": "chim 3 canh 2" }
				]
			}
		},
		"bones": {
			"wing_1": {
				"rotate": [
					{ "time": 0.2667 },
					{ "time": 0.9333, "value": -4.59 },
					{ "time": 1.6 },
					{ "time": 2.2667, "value": -4.59 },
					{ "time": 2.9333 },
					{ "time": 3.6, "value": -4.59 },
					{ "time": 4.2667 },
					{ "time": 4.9333, "value": -4.59 },
					{ "time": 5.6 },
					{ "time": 6.2667, "value": -4.59 },
					{ "time": 6.9333 },
					{ "time": 7.6, "value": -4.59 },
					{ "time": 8.2667 },
					{ "time": 8.9333, "value": -4.59 },
					{ "time": 9.6 },
					{ "time": 10.2667, "value": -4.59 },
					{ "time": 23.5333 },
					{ "time": 24.2, "value": -4.59 },
					{ "time": 24.8667 },
					{ "time": 25.5333, "value": -4.59 },
					{ "time": 26.2 },
					{ "time": 26.8667, "value": -4.59 },
					{ "time": 27.5333 },
					{ "time": 28.2, "value": -4.59 },
					{ "time": 28.8667 },
					{ "time": 29.5333, "value": -4.59 },
					{ "time": 30.2 },
					{ "time": 30.8667, "value": -4.59 },
					{ "time": 31.5333 },
					{ "time": 32.2, "value": -4.59 },
					{ "time": 32.8667 },
					{ "time": 33.5333, "value": -4.59 },
					{ "time": 37.1333 },
					{ "time": 37.8, "value": -4.59 },
					{ "time": 38.4667 },
					{ "time": 39.1333, "value": -4.59 },
					{ "time": 39.8 },
					{ "time": 40.4667, "value": -4.59 },
					{ "time": 41.1333 },
					{ "time": 41.8, "value": -4.59 },
					{ "time": 42.4667 },
					{ "time": 43.1333, "value": -4.59 },
					{ "time": 43.8 },
					{ "time": 44.4667, "value": -4.59 },
					{ "time": 45.1333 },
					{ "time": 45.8, "value": -4.59 },
					{ "time": 46.4667 },
					{ "time": 47.1333, "value": -4.59 }
				]
			},
			"wing_1_2": {
				"rotate": [
					{ "time": 0.2667 },
					{ "time": 0.9333, "value": -17.36 },
					{ "time": 1.6 },
					{ "time": 2.2667, "value": -17.36 },
					{ "time": 2.9333 },
					{ "time": 3.6, "value": -17.36 },
					{ "time": 4.2667 },
					{ "time": 4.9333, "value": -17.36 },
					{ "time": 5.6 },
					{ "time": 6.2667, "value": -17.36 },
					{ "time": 6.9333 },
					{ "time": 7.6, "value": -17.36 },
					{ "time": 8.2667 },
					{ "time": 8.9333, "value": -17.36 },
					{ "time": 9.6 },
					{ "time": 10.2667, "value": -17.36 },
					{ "time": 23.5333 },
					{ "time": 24.2, "value": -17.36 },
					{ "time": 24.8667 },
					{ "time": 25.5333, "value": -17.36 },
					{ "time": 26.2 },
					{ "time": 26.8667, "value": -17.36 },
					{ "time": 27.5333 },
					{ "time": 28.2, "value": -17.36 },
					{ "time": 28.8667 },
					{ "time": 29.5333, "value": -17.36 },
					{ "time": 30.2 },
					{ "time": 30.8667, "value": -17.36 },
					{ "time": 31.5333 },
					{ "time": 32.2, "value": -17.36 },
					{ "time": 32.8667 },
					{ "time": 33.5333, "value": -17.36 },
					{ "time": 37.1333 },
					{ "time": 37.8, "value": -17.36 },
					{ "time": 38.4667 },
					{ "time": 39.1333, "value": -17.36 },
					{ "time": 39.8 },
					{ "time": 40.4667, "value": -17.36 },
					{ "time": 41.1333 },
					{ "time": 41.8, "value": -17.36 },
					{ "time": 42.4667 },
					{ "time": 43.1333, "value": -17.36 },
					{ "time": 43.8 },
					{ "time": 44.4667, "value": -17.36 },
					{ "time": 45.1333 },
					{ "time": 45.8, "value": -17.36 },
					{ "time": 46.4667 },
					{ "time": 47.1333, "value": -17.36 }
				]
			},
			"wing_2": {
				"rotate": [
					{ "time": 0.2667 },
					{ "time": 0.9333, "value": 4.76 },
					{ "time": 1.6 },
					{ "time": 2.2667, "value": 4.76 },
					{ "time": 2.9333 },
					{ "time": 3.6, "value": 4.76 },
					{ "time": 4.2667 },
					{ "time": 4.9333, "value": 4.76 },
					{ "time": 5.6 },
					{ "time": 6.2667, "value": 4.76 },
					{ "time": 6.9333 },
					{ "time": 7.6, "value": 4.76 },
					{ "time": 8.2667 },
					{ "time": 8.9333, "value": 4.76 },
					{ "time": 9.6 },
					{ "time": 10.2667, "value": 4.76 },
					{ "time": 23.5333 },
					{ "time": 24.2, "value": 4.76 },
					{ "time": 24.8667 },
					{ "time": 25.5333, "value": 4.76 },
					{ "time": 26.2 },
					{ "time": 26.8667, "value": 4.76 },
					{ "time": 27.5333 },
					{ "time": 28.2, "value": 4.76 },
					{ "time": 28.8667 },
					{ "time": 29.5333, "value": 4.76 },
					{ "time": 30.2 },
					{ "time": 30.8667, "value": 4.76 },
					{ "time": 31.5333 },
					{ "time": 32.2, "value": 4.76 },
					{ "time": 32.8667 },
					{ "time": 33.5333, "value": 4.76 },
					{ "time": 37.1333 },
					{ "time": 37.8, "value": 4.76 },
					{ "time": 38.4667 },
					{ "time": 39.1333, "value": 4.76 },
					{ "time": 39.8 },
					{ "time": 40.4667, "value": 4.76 },
					{ "time": 41.1333 },
					{ "time": 41.8, "value": 4.76 },
					{ "time": 42.4667 },
					{ "time": 43.1333, "value": 4.76 },
					{ "time": 43.8 },
					{ "time": 44.4667, "value": 4.76 },
					{ "time": 45.1333 },
					{ "time": 45.8, "value": 4.76 },
					{ "time": 46.4667 },
					{ "time": 47.1333, "value": 4.76 }
				]
			},
			"wing_2_2": {
				"rotate": [
					{ "time": 0.2667 },
					{ "time": 0.9333, "value": 17.19 },
					{ "time": 1.6 },
					{ "time": 2.2667, "value": 17.19 },
					{ "time": 2.9333 },
					{ "time": 3.6, "value": 17.19 },
					{ "time": 4.2667 },
					{ "time": 4.9333, "value": 17.19 },
					{ "time": 5.6 },
					{ "time": 6.2667, "value": 17.19 },
					{ "time": 6.9333 },
					{ "time": 7.6, "value": 17.19 },
					{ "time": 8.2667 },
					{ "time": 8.9333, "value": 17.19 },
					{ "time": 9.6 },
					{ "time": 10.2667, "value": 17.19 },
					{ "time": 23.5333 },
					{ "time": 24.2, "value": 17.19 },
					{ "time": 24.8667 },
					{ "time": 25.5333, "value": 17.19 },
					{ "time": 26.2 },
					{ "time": 26.8667, "value": 17.19 },
					{ "time": 27.5333 },
					{ "time": 28.2, "value": 17.19 },
					{ "time": 28.8667 },
					{ "time": 29.5333, "value": 17.19 },
					{ "time": 30.2 },
					{ "time": 30.8667, "value": 17.19 },
					{ "time": 31.5333 },
					{ "time": 32.2, "value": 17.19 },
					{ "time": 32.8667 },
					{ "time": 33.5333, "value": 17.19 },
					{ "time": 37.1333 },
					{ "time": 37.8, "value": 17.19 },
					{ "time": 38.4667 },
					{ "time": 39.1333, "value": 17.19 },
					{ "time": 39.8 },
					{ "time": 40.4667, "value": 17.19 },
					{ "time": 41.1333 },
					{ "time": 41.8, "value": 17.19 },
					{ "time": 42.4667 },
					{ "time": 43.1333, "value": 17.19 },
					{ "time": 43.8 },
					{ "time": 44.4667, "value": 17.19 },
					{ "time": 45.1333 },
					{ "time": 45.8, "value": 17.19 },
					{ "time": 46.4667 },
					{ "time": 47.1333, "value": 17.19 }
				]
			},
			"body chim 3": {
				"scale": [
					{ "time": 1.9667, "y": -1 }
				]
			},
			"chim 3 canh 1": {
				"rotate": [
					{ "time": 1.9667, "value": -31.78 },
					{ "time": 2.6333, "value": -8.91 },
					{ "time": 3.3, "value": -31.78 },
					{ "time": 3.9667, "value": -8.91 },
					{ "time": 4.6333, "value": -31.78 },
					{ "time": 5.3, "value": -8.91 },
					{ "time": 5.9667, "value": -31.78 },
					{ "time": 6.6333, "value": -8.91 },
					{ "time": 7.3, "value": -31.78 },
					{ "time": 7.9667, "value": -8.91 },
					{ "time": 8.6333, "value": -31.78 },
					{ "time": 9.3, "value": -8.91 },
					{ "time": 9.9667, "value": -31.78 },
					{ "time": 10.6333, "value": -8.91 },
					{ "time": 11.3, "value": -31.78 },
					{ "time": 11.9667, "value": -8.91 },
					{ "time": 22.4, "value": -31.78 },
					{ "time": 23.0667, "value": -8.91 },
					{ "time": 23.7333, "value": -31.78 },
					{ "time": 24.4, "value": -8.91 },
					{ "time": 25.0667, "value": -31.78 },
					{ "time": 25.7333, "value": -8.91 },
					{ "time": 26.4, "value": -31.78 },
					{ "time": 27.0667, "value": -8.91 },
					{ "time": 27.7333, "value": -31.78 },
					{ "time": 28.4, "value": -8.91 },
					{ "time": 29.0667, "value": -31.78 },
					{ "time": 29.7333, "value": -8.91 },
					{ "time": 30.4, "value": -31.78 },
					{ "time": 31.0667, "value": -8.91 },
					{ "time": 31.7333, "value": -31.78 },
					{ "time": 32.4, "value": -8.91 },
					{ "time": 41.4667, "value": -31.78 },
					{ "time": 42.1333, "value": -8.91 },
					{ "time": 42.8, "value": -31.78 },
					{ "time": 43.4667, "value": -8.91 },
					{ "time": 44.1333, "value": -31.78 },
					{ "time": 44.8, "value": -8.91 },
					{ "time": 45.4667, "value": -31.78 },
					{ "time": 46.1333, "value": -8.91 },
					{ "time": 46.8, "value": -31.78 },
					{ "time": 47.4667, "value": -8.91 },
					{ "time": 48.1333, "value": -31.78 },
					{ "time": 48.8, "value": -8.91 },
					{ "time": 49.4667, "value": -31.78 },
					{ "time": 50.1333, "value": -8.91 },
					{ "time": 50.8, "value": -31.78 },
					{ "time": 51.4667, "value": -8.91 }
				]
			},
			"chim 3 canh 2": {
				"rotate": [
					{ "time": 1.9667 },
					{ "time": 2.6333, "value": -20.08 },
					{ "time": 3.3 },
					{ "time": 3.9667, "value": -20.08 },
					{ "time": 4.6333 },
					{ "time": 5.3, "value": -20.08 },
					{ "time": 5.9667 },
					{ "time": 6.6333, "value": -20.08 },
					{ "time": 7.3 },
					{ "time": 7.9667, "value": -20.08 },
					{ "time": 8.6333 },
					{ "time": 9.3, "value": -20.08 },
					{ "time": 9.9667 },
					{ "time": 10.6333, "value": -20.08 },
					{ "time": 11.3 },
					{ "time": 11.9667, "value": -20.08 },
					{ "time": 22.4 },
					{ "time": 23.0667, "value": -20.08 },
					{ "time": 23.7333 },
					{ "time": 24.4, "value": -20.08 },
					{ "time": 25.0667 },
					{ "time": 25.7333, "value": -20.08 },
					{ "time": 26.4 },
					{ "time": 27.0667, "value": -20.08 },
					{ "time": 27.7333 },
					{ "time": 28.4, "value": -20.08 },
					{ "time": 29.0667 },
					{ "time": 29.7333, "value": -20.08 },
					{ "time": 30.4 },
					{ "time": 31.0667, "value": -20.08 },
					{ "time": 31.7333 },
					{ "time": 32.4, "value": -20.08 },
					{ "time": 41.4667 },
					{ "time": 42.1333, "value": -20.08 },
					{ "time": 42.8 },
					{ "time": 43.4667, "value": -20.08 },
					{ "time": 44.1333 },
					{ "time": 44.8, "value": -20.08 },
					{ "time": 45.4667 },
					{ "time": 46.1333, "value": -20.08 },
					{ "time": 46.8 },
					{ "time": 47.4667, "value": -20.08 },
					{ "time": 48.1333 },
					{ "time": 48.8, "value": -20.08 },
					{ "time": 49.4667 },
					{ "time": 50.1333, "value": -20.08 },
					{ "time": 50.8 },
					{ "time": 51.4667, "value": -20.08 }
				],
				"translate": [
					{ "time": 1.9667, "x": 0.09, "y": 6.02 }
				]
			},
			"chim 2 canh 1": {
				"rotate": [
					{ "time": 12.9667, "value": 57.31 },
					{ "time": 13.6333, "value": 9.25 },
					{ "time": 14.3, "value": 57.31 },
					{ "time": 14.9667, "value": 9.25 },
					{ "time": 15.6333, "value": 57.31 },
					{ "time": 16.3, "value": 9.25 },
					{ "time": 16.9667, "value": 57.31 },
					{ "time": 17.6333, "value": 9.25 },
					{ "time": 18.3, "value": 57.31 },
					{ "time": 18.9667, "value": 9.25 },
					{ "time": 19.6333, "value": 57.31 },
					{ "time": 20.3, "value": 9.25 },
					{ "time": 20.9667, "value": 57.31 },
					{ "time": 21.6333, "value": 9.25 },
					{ "time": 22.3, "value": 57.31 },
					{ "time": 22.9667, "value": 9.25 },
					{ "time": 28.8333, "value": 57.31 },
					{ "time": 29.5, "value": 9.25 },
					{ "time": 30.1667, "value": 57.31 },
					{ "time": 30.8333, "value": 9.25 },
					{ "time": 31.5, "value": 57.31 },
					{ "time": 32.1667, "value": 9.25 },
					{ "time": 32.8333, "value": 57.31 },
					{ "time": 33.5, "value": 9.25 },
					{ "time": 34.1667, "value": 57.31 },
					{ "time": 34.8333, "value": 9.25 },
					{ "time": 35.5, "value": 57.31 },
					{ "time": 36.1667, "value": 9.25 },
					{ "time": 36.8333, "value": 57.31 },
					{ "time": 37.5, "value": 9.25 },
					{ "time": 38.1667, "value": 57.31 },
					{ "time": 38.8333, "value": 9.25 },
					{ "time": 44.3333, "value": 57.31 },
					{ "time": 45, "value": 9.25 },
					{ "time": 45.6667, "value": 57.31 },
					{ "time": 46.3333, "value": 9.25 },
					{ "time": 47, "value": 57.31 },
					{ "time": 47.6667, "value": 9.25 },
					{ "time": 48.3333, "value": 57.31 },
					{ "time": 49, "value": 9.25 },
					{ "time": 49.6667, "value": 57.31 },
					{ "time": 50.3333, "value": 9.25 },
					{ "time": 51, "value": 57.31 },
					{ "time": 51.6667, "value": 9.25 },
					{ "time": 52.3333, "value": 57.31 },
					{ "time": 53, "value": 9.25 },
					{ "time": 53.6667, "value": 57.31 },
					{ "time": 54.3333, "value": 9.25 }
				]
			},
			"chim 2 canh 2": {
				"rotate": [
					{ "time": 12.9667 },
					{ "time": 13.6333, "value": 43.11 },
					{ "time": 14.3 },
					{ "time": 14.9667, "value": 43.11 },
					{ "time": 15.6333 },
					{ "time": 16.3, "value": 43.11 },
					{ "time": 16.9667 },
					{ "time": 17.6333, "value": 43.11 },
					{ "time": 18.3 },
					{ "time": 18.9667, "value": 43.11 },
					{ "time": 19.6333 },
					{ "time": 20.3, "value": 43.11 },
					{ "time": 20.9667 },
					{ "time": 21.6333, "value": 43.11 },
					{ "time": 22.3 },
					{ "time": 22.9667, "value": 43.11 },
					{ "time": 28.8333 },
					{ "time": 29.5, "value": 43.11 },
					{ "time": 30.1667 },
					{ "time": 30.8333, "value": 43.11 },
					{ "time": 31.5 },
					{ "time": 32.1667, "value": 43.11 },
					{ "time": 32.8333 },
					{ "time": 33.5, "value": 43.11 },
					{ "time": 34.1667 },
					{ "time": 34.8333, "value": 43.11 },
					{ "time": 35.5 },
					{ "time": 36.1667, "value": 43.11 },
					{ "time": 36.8333 },
					{ "time": 37.5, "value": 43.11 },
					{ "time": 38.1667 },
					{ "time": 38.8333, "value": 43.11 },
					{ "time": 44.3333 },
					{ "time": 45, "value": 43.11 },
					{ "time": 45.6667 },
					{ "time": 46.3333, "value": 43.11 },
					{ "time": 47 },
					{ "time": 47.6667, "value": 43.11 },
					{ "time": 48.3333 },
					{ "time": 49, "value": 43.11 },
					{ "time": 49.6667 },
					{ "time": 50.3333, "value": 43.11 },
					{ "time": 51 },
					{ "time": 51.6667, "value": 43.11 },
					{ "time": 52.3333 },
					{ "time": 53, "value": 43.11 },
					{ "time": 53.6667 },
					{ "time": 54.3333, "value": 43.11 }
				]
			}
		},
		"path": {
			"Fly_path_chim_3": {
				"position": [
					{ "time": 1.9667 },
					{ "time": 11.9667, "value": 1, "curve": "stepped" },
					{ "time": 22.4 },
					{ "time": 32.4, "value": 1, "curve": "stepped" },
					{ "time": 41.4667 },
					{ "time": 51.4667, "value": 1 }
				]
			},
			"fly_path_chim_1": {
				"position": [
					{ "time": 0.2667 },
					{ "time": 10.2667, "value": 1, "curve": "stepped" },
					{ "time": 23.5333 },
					{ "time": 33.5333, "value": 1, "curve": "stepped" },
					{ "time": 37.1333 },
					{ "time": 47.1333, "value": 1 }
				]
			},
			"fly_path_chim_4": {
				"position": [
					{ "time": 12.9667 },
					{ "time": 22.9667, "value": 1, "curve": "stepped" },
					{ "time": 28.8333 },
					{ "time": 38.8333, "value": 1, "curve": "stepped" },
					{ "time": 44.3333 },
					{ "time": 54.3333, "value": 1 }
				]
			}
		}
	},
	"Idle": {
		"slots": {
			"body chim 2": {
				"attachment": [
					{ "name": "body chim 2" }
				]
			},
			"body chim 3": {
				"attachment": [
					{ "name": "body chim 3" }
				]
			},
			"chim 1": {
				"attachment": [
					{ "name": "chim 1" }
				]
			},
			"chim 2 canh 1": {
				"attachment": [
					{ "name": "chim 2 canh 1" }
				]
			},
			"chim 2 canh 2": {
				"attachment": [
					{ "name": "chim 2 canh 2" }
				]
			},
			"chim 3 canh 1": {
				"attachment": [
					{ "name": "chim 3 canh 1" }
				]
			},
			"chim 3 canh 2": {
				"attachment": [
					{ "name": "chim 3 canh 2" }
				]
			}
		},
		"bones": {
			"body chim 3": {
				"rotate": [
					{ "value": -150.82 }
				],
				"translate": [
					{},
					{ "time": 0.6333, "y": -8.91 },
					{ "time": 1.3 },
					{ "time": 1.9667, "y": -8.91 },
					{ "time": 2.6333 }
				],
				"scale": [
					{ "y": -1 }
				]
			},
			"chim 3 canh 1": {
				"rotate": [
					{
						"curve": [ 0.12, 0, 0.246, 21.08 ]
					},
					{
						"time": 0.3667,
						"value": 21.08,
						"curve": [ 0.461, 21.08, 0.539, 0 ]
					},
					{
						"time": 0.6333,
						"curve": [ 0.728, 0, 0.839, 21.08 ]
					},
					{
						"time": 0.9333,
						"value": 21.08,
						"curve": [ 1.054, 21.08, 1.18, 0 ]
					},
					{
						"time": 1.3,
						"curve": [ 1.42, 0, 1.513, 21.08 ]
					},
					{
						"time": 1.6333,
						"value": 21.08,
						"curve": [ 1.728, 21.08, 1.839, 0 ]
					},
					{
						"time": 1.9333,
						"curve": [ 2.028, 0, 2.106, 21.08 ]
					},
					{
						"time": 2.2,
						"value": 21.08,
						"curve": [ 2.32, 21.08, 2.446, 7.03 ]
					},
					{ "time": 2.5667 }
				]
			},
			"chim 3 canh 2": {
				"rotate": [
					{
						"curve": [ 0.12, 0, 0.246, -11.48 ]
					},
					{
						"time": 0.3667,
						"value": -11.48,
						"curve": [ 0.461, -11.48, 0.539, 0 ]
					},
					{
						"time": 0.6333,
						"curve": [ 0.728, 0, 0.839, -11.48 ]
					},
					{
						"time": 0.9333,
						"value": -11.48,
						"curve": [ 1.054, -11.48, 1.18, 0 ]
					},
					{
						"time": 1.3,
						"curve": [ 1.42, 0, 1.513, -11.48 ]
					},
					{
						"time": 1.6333,
						"value": -11.48,
						"curve": [ 1.728, -11.48, 1.839, 0 ]
					},
					{
						"time": 1.9333,
						"curve": [ 2.028, 0, 2.106, -11.48 ]
					},
					{
						"time": 2.2,
						"value": -11.48,
						"curve": [ 2.32, -11.48, 2.446, -3.83 ]
					},
					{ "time": 2.5667 }
				]
			},
			"body chim 4": {
				"translate": [
					{
						"curve": [ 0.56, 0, 0.871, 0, 0.57, 0, 0.871, -21.26 ]
					},
					{
						"time": 1.3,
						"y": -21.26,
						"curve": [ 1.729, 0, 2.137, 0, 1.729, -21.26, 2.137, -7.09 ]
					},
					{ "time": 2.5667 }
				]
			},
			"chim 2 canh 1": {
				"rotate": [
					{
						"curve": [ 0.12, 0, 0.246, -22.35 ]
					},
					{
						"time": 0.3667,
						"value": -22.35,
						"curve": [ 0.461, -22.35, 0.539, 0 ]
					},
					{
						"time": 0.6333,
						"curve": [ 0.736, 0, 0.864, -22.35 ]
					},
					{
						"time": 0.9667,
						"value": -22.35,
						"curve": [ 1.078, -22.35, 1.188, 0 ]
					},
					{
						"time": 1.3,
						"curve": [ 1.42, 0, 1.513, -22.35 ]
					},
					{
						"time": 1.6333,
						"value": -22.35,
						"curve": [ 1.728, -22.35, 1.839, 0 ]
					},
					{
						"time": 1.9333,
						"curve": [ 2.036, 0, 2.13, -22.35 ]
					},
					{
						"time": 2.2333,
						"value": -22.35,
						"curve": [ 2.345, -22.35, 2.455, -7.45 ]
					},
					{ "time": 2.5667 }
				]
			},
			"chim 2 canh 2": {
				"rotate": [
					{
						"curve": [ 0.12, 0, 0.246, 22.03 ]
					},
					{
						"time": 0.3667,
						"value": 22.03,
						"curve": [ 0.461, 22.03, 0.539, 0 ]
					},
					{
						"time": 0.6333,
						"curve": [ 0.736, 0, 0.864, 22.03 ]
					},
					{
						"time": 0.9667,
						"value": 22.03,
						"curve": [ 1.078, 22.03, 1.188, 0 ]
					},
					{
						"time": 1.3,
						"curve": [ 1.42, 0, 1.513, 22.03 ]
					},
					{
						"time": 1.6333,
						"value": 22.03,
						"curve": [ 1.728, 22.03, 1.839, 0 ]
					},
					{
						"time": 1.9333,
						"curve": [ 2.036, 0, 2.13, 22.03 ]
					},
					{
						"time": 2.2333,
						"value": 22.03,
						"curve": [ 2.345, 22.03, 2.455, 7.34 ]
					},
					{ "time": 2.5667 }
				]
			},
			"chim 1": {
				"rotate": [
					{
						"curve": [ 0.215, 0, 0.419, 5.35 ]
					},
					{
						"time": 0.6333,
						"value": 5.35,
						"curve": [ 0.848, 5.35, 1.085, 6.08 ]
					},
					{
						"time": 1.3,
						"value": 4.1,
						"curve": [ 1.515, 2.11, 1.719, -1.63 ]
					},
					{
						"time": 1.9333,
						"value": -1.63,
						"curve": [ 2.148, -1.63, 2.352, -0.54 ]
					},
					{ "time": 2.5667 }
				],
				"translate": [
					{
						"curve": [ 0.215, 0, 0.419, 7.39, 0.215, 0, 0.419, 2.15 ]
					},
					{
						"time": 0.6333,
						"x": 7.39,
						"y": 2.15,
						"curve": [ 0.848, 7.39, 1.085, -3.02, 0.848, 2.15, 1.085, -2.05 ]
					},
					{
						"time": 1.3,
						"x": -3.02,
						"y": -2.05,
						"curve": [ 1.515, -3.02, 1.719, 8.98, 1.515, -2.05, 1.719, 4.68 ]
					},
					{
						"time": 1.9333,
						"x": 8.98,
						"y": 4.68,
						"curve": [ 2.148, 8.98, 2.352, 1.02, 2.148, 4.68, 2.352, 0.92 ]
					},
					{ "time": 2.5667 }
				]
			}
		}
	},
	"seagulls": {
		"slots": {
			"body chim 2": {
				"attachment": [
					{ "name": "body chim 2" }
				]
			},
			"body chim 3": {
				"attachment": [
					{ "name": "body chim 3" }
				]
			},
			"chim 1": {
				"attachment": [
					{ "name": "chim 1" }
				]
			},
			"chim 2 canh 1": {
				"attachment": [
					{ "name": "chim 2 canh 1" }
				]
			},
			"chim 2 canh 2": {
				"attachment": [
					{ "name": "chim 2 canh 2" }
				]
			},
			"chim 3 canh 1": {
				"attachment": [
					{ "name": "chim 3 canh 1" }
				]
			},
			"chim 3 canh 2": {
				"attachment": [
					{ "name": "chim 3 canh 2" }
				]
			}
		},
		"bones": {
			"body chim 3": {
				"rotate": [
					{ "value": -150.82 }
				],
				"translate": [
					{},
					{ "time": 0.8333, "y": -8.91 },
					{ "time": 1.7 },
					{ "time": 2.5333, "y": -8.91 },
					{ "time": 3.4 }
				],
				"scale": [
					{ "y": -1 }
				]
			},
			"chim 3 canh 2": {
				"rotate": [
					{
						"curve": [ 0.156, 0, 0.311, -11.48 ]
					},
					{
						"time": 0.4667,
						"value": -11.48,
						"curve": [ 0.589, -11.48, 0.711, 0 ]
					},
					{
						"time": 0.8333,
						"curve": [ 0.956, 0, 1.078, -11.48 ]
					},
					{
						"time": 1.2,
						"value": -11.48,
						"curve": [ 1.356, -11.48, 1.511, 0 ]
					},
					{
						"time": 1.6667,
						"curve": [ 1.822, 0, 1.978, -11.48 ]
					},
					{
						"time": 2.1333,
						"value": -11.48,
						"curve": [ 2.256, -11.48, 2.378, 0 ]
					},
					{
						"time": 2.5,
						"curve": [ 2.622, 0, 2.744, -11.48 ]
					},
					{
						"time": 2.8667,
						"value": -11.48,
						"curve": [ 3.022, -11.48, 3.178, -3.83 ]
					},
					{ "time": 3.3333 }
				]
			},
			"chim 3 canh 1": {
				"rotate": [
					{
						"curve": [ 0.156, 0, 0.311, 21.08 ]
					},
					{
						"time": 0.4667,
						"value": 21.08,
						"curve": [ 0.589, 21.08, 0.711, 0 ]
					},
					{
						"time": 0.8333,
						"curve": [ 0.956, 0, 1.078, 21.08 ]
					},
					{
						"time": 1.2,
						"value": 21.08,
						"curve": [ 1.356, 21.08, 1.511, 0 ]
					},
					{
						"time": 1.6667,
						"curve": [ 1.822, 0, 1.978, 21.08 ]
					},
					{
						"time": 2.1333,
						"value": 21.08,
						"curve": [ 2.256, 21.08, 2.378, 0 ]
					},
					{
						"time": 2.5,
						"curve": [ 2.622, 0, 2.744, 21.08 ]
					},
					{
						"time": 2.8667,
						"value": 21.08,
						"curve": [ 3.022, 21.08, 3.178, 7.03 ]
					},
					{ "time": 3.3333 }
				]
			},
			"body chim 4": {
				"translate": [
					{
						"curve": [ 0.725, 0, 1.111, 0, 0.738, 0, 1.111, -21.26 ]
					},
					{
						"time": 1.6667,
						"y": -21.26,
						"curve": [ 2.222, 0, 2.778, 0, 2.222, -21.26, 2.778, -7.09 ]
					},
					{ "time": 3.3333 }
				]
			},
			"chim 2 canh 2": {
				"rotate": [
					{
						"curve": [ 0.156, 0, 0.311, 22.03 ]
					},
					{
						"time": 0.4667,
						"value": 22.03,
						"curve": [ 0.589, 22.03, 0.711, 0 ]
					},
					{
						"time": 0.8333,
						"curve": [ 0.967, 0, 1.1, 22.03 ]
					},
					{
						"time": 1.2333,
						"value": 22.03,
						"curve": [ 1.378, 22.03, 1.522, 0 ]
					},
					{
						"time": 1.6667,
						"curve": [ 1.822, 0, 1.978, 22.03 ]
					},
					{
						"time": 2.1333,
						"value": 22.03,
						"curve": [ 2.256, 22.03, 2.378, 0 ]
					},
					{
						"time": 2.5,
						"curve": [ 2.633, 0, 2.767, 22.03 ]
					},
					{
						"time": 2.9,
						"value": 22.03,
						"curve": [ 3.044, 22.03, 3.189, 7.34 ]
					},
					{ "time": 3.3333 }
				]
			},
			"chim 2 canh 1": {
				"rotate": [
					{
						"curve": [ 0.156, 0, 0.311, -22.35 ]
					},
					{
						"time": 0.4667,
						"value": -22.35,
						"curve": [ 0.589, -22.35, 0.711, 0 ]
					},
					{
						"time": 0.8333,
						"curve": [ 0.967, 0, 1.1, -22.35 ]
					},
					{
						"time": 1.2333,
						"value": -22.35,
						"curve": [ 1.378, -22.35, 1.522, 0 ]
					},
					{
						"time": 1.6667,
						"curve": [ 1.822, 0, 1.978, -22.35 ]
					},
					{
						"time": 2.1333,
						"value": -22.35,
						"curve": [ 2.256, -22.35, 2.378, 0 ]
					},
					{
						"time": 2.5,
						"curve": [ 2.633, 0, 2.767, -22.35 ]
					},
					{
						"time": 2.9,
						"value": -22.35,
						"curve": [ 3.044, -22.35, 3.189, -7.45 ]
					},
					{ "time": 3.3333 }
				]
			},
			"chim 1": {
				"rotate": [
					{
						"curve": [ 0.278, 0, 0.556, 5.35 ]
					},
					{
						"time": 0.8333,
						"value": 5.35,
						"curve": [ 1.111, 5.35, 1.389, 6.08 ]
					},
					{
						"time": 1.6667,
						"value": 4.1,
						"curve": [ 1.944, 2.11, 2.222, -1.63 ]
					},
					{
						"time": 2.5,
						"value": -1.63,
						"curve": [ 2.778, -1.63, 3.056, -0.54 ]
					},
					{ "time": 3.3333 }
				],
				"translate": [
					{
						"curve": [ 0.278, 0, 0.556, 7.39, 0.278, 0, 0.556, 2.15 ]
					},
					{
						"time": 0.8333,
						"x": 7.39,
						"y": 2.15,
						"curve": [ 1.111, 7.39, 1.389, -3.02, 1.111, 2.15, 1.389, -2.05 ]
					},
					{
						"time": 1.6667,
						"x": -3.02,
						"y": -2.05,
						"curve": [ 1.944, -3.02, 2.222, 8.98, 1.944, -2.05, 2.222, 4.68 ]
					},
					{
						"time": 2.5,
						"x": 8.98,
						"y": 4.68,
						"curve": [ 2.778, 8.98, 3.056, 1.02, 2.778, 4.68, 3.056, 0.92 ]
					},
					{ "time": 3.3333 }
				]
			}
		}
	}
}
}